[
    {
        "anonymous": false,
        "inputs": [
            {
                "indexed": false,
                "internalType": "uint8",
                "name": "version",
                "type": "uint8"
            }
        ],
        "name": "Initialized",
        "type": "event"
    },
    {
        "anonymous": false,
        "inputs": [
            {
                "indexed": true,
                "internalType": "address",
                "name": "device",
                "type": "address"
            },
            {
                "indexed": false,
                "internalType": "address",
                "name": "owner",
                "type": "address"
            },
            {
                "indexed": false,
                "internalType": "bytes32",
                "name": "hash",
                "type": "bytes32"
            },
            {
                "indexed": false,
                "internalType": "string",
                "name": "uri",
                "type": "string"
            }
        ],
        "name": "NewDevice",
        "type": "event"
    },
    {
        "anonymous": false,
        "inputs": [
            {
                "indexed": true,
                "internalType": "address",
                "name": "device",
                "type": "address"
            },
            {
                "indexed": false,
                "internalType": "address",
                "name": "owner",
                "type": "address"
            }
        ],
        "name": "RemoveDevice",
        "type": "event"
    },
    {
        "anonymous": false,
        "inputs": [
            {
                "indexed": true,
                "internalType": "address",
                "name": "store",
                "type": "address"
            }
        ],
        "name": "SetIoIdStore",
        "type": "event"
    },
    {
        "anonymous": false,
        "inputs": [
            {
                "indexed": true,
                "internalType": "address",
                "name": "device",
                "type": "address"
            },
            {
                "indexed": false,
                "internalType": "address",
                "name": "owner",
                "type": "address"
            },
            {
                "indexed": false,
                "internalType": "bytes32",
                "name": "hash",
                "type": "bytes32"
            },
            {
                "indexed": false,
                "internalType": "string",
                "name": "uri",
                "type": "string"
            }
        ],
        "name": "UpdateDevice",
        "type": "event"
    },
    {
        "inputs": [],
        "name": "DOMAIN_SEPARATOR",
        "outputs": [
            {
                "internalType": "bytes32",
                "name": "",
                "type": "bytes32"
            }
        ],
        "stateMutability": "view",
        "type": "function"
    },
    {
        "inputs": [],
        "name": "EIP712DOMAIN_TYPEHASH",
        "outputs": [
            {
                "internalType": "bytes32",
                "name": "",
                "type": "bytes32"
            }
        ],
        "stateMutability": "view",
        "type": "function"
    },
    {
        "inputs": [],
        "name": "METHOD",
        "outputs": [
            {
                "internalType": "string",
                "name": "",
                "type": "string"
            }
        ],
        "stateMutability": "view",
        "type": "function"
    },
    {
        "inputs": [
            {
                "internalType": "address",
                "name": "device",
                "type": "address"
            }
        ],
        "name": "deviceTokenId",
        "outputs": [
            {
                "internalType": "uint256",
                "name": "",
                "type": "uint256"
            }
        ],
        "stateMutability": "view",
        "type": "function"
    },
    {
        "inputs": [
            {
                "internalType": "address",
                "name": "device",
                "type": "address"
            }
        ],
        "name": "documentHash",
        "outputs": [
            {
                "internalType": "bytes32",
                "name": "",
                "type": "bytes32"
            }
        ],
        "stateMutability": "view",
        "type": "function"
    },
    {
        "inputs": [
            {
                "internalType": "address",
                "name": "device",
                "type": "address"
            }
        ],
        "name": "documentID",
        "outputs": [
            {
                "internalType": "string",
                "name": "",
                "type": "string"
            }
        ],
        "stateMutability": "pure",
        "type": "function"
    },
    {
        "inputs": [
            {
                "internalType": "address",
                "name": "device",
                "type": "address"
            }
        ],
        "name": "documentURI",
        "outputs": [
            {
                "internalType": "string",
                "name": "",
                "type": "string"
            }
        ],
        "stateMutability": "view",
        "type": "function"
    },
    {
        "inputs": [
            {
                "internalType": "address",
                "name": "device",
                "type": "address"
            }
        ],
        "name": "exists",
        "outputs": [
            {
                "internalType": "bool",
                "name": "",
                "type": "bool"
            }
        ],
        "stateMutability": "view",
        "type": "function"
    },
    {
        "inputs": [
            {
                "internalType": "address",
                "name": "_ioIDStore",
                "type": "address"
            },
            {
                "internalType": "address",
                "name": "_ioID",
                "type": "address"
            }
        ],
        "name": "initialize",
        "outputs": [],
        "stateMutability": "nonpayable",
        "type": "function"
    },
    {
        "inputs": [],
        "name": "ioID",
        "outputs": [
            {
                "internalType": "address",
                "name": "",
                "type": "address"
            }
        ],
        "stateMutability": "view",
        "type": "function"
    },
    {
        "inputs": [],
        "name": "ioIDStore",
        "outputs": [
            {
                "internalType": "address",
                "name": "",
                "type": "address"
            }
        ],
        "stateMutability": "view",
        "type": "function"
    },
    {
        "inputs": [
            {
                "internalType": "address",
                "name": "device",
                "type": "address"
            }
        ],
        "name": "nonces",
        "outputs": [
            {
                "internalType": "uint256",
                "name": "",
                "type": "uint256"
            }
        ],
        "stateMutability": "view",
        "type": "function"
    },
    {
        "inputs": [
            {
                "internalType": "address",
                "name": "owner",
                "type": "address"
            },
            {
                "internalType": "address",
                "name": "device",
                "type": "address"
            }
        ],
        "name": "permitHash",
        "outputs": [
            {
                "internalType": "bytes32",
                "name": "",
                "type": "bytes32"
            }
        ],
        "stateMutability": "view",
        "type": "function"
    },
    {
        "inputs": [
            {
                "internalType": "address",
                "name": "deviceContract",
                "type": "address"
            },
            {
                "internalType": "uint256",
                "name": "tokenId",
                "type": "uint256"
            },
            {
                "internalType": "address",
                "name": "device",
                "type": "address"
            },
            {
                "internalType": "bytes32",
                "name": "hash",
                "type": "bytes32"
            },
            {
                "internalType": "string",
                "name": "uri",
                "type": "string"
            },
            {
                "internalType": "uint8",
                "name": "v",
                "type": "uint8"
            },
            {
                "internalType": "bytes32",
                "name": "r",
                "type": "bytes32"
            },
            {
                "internalType": "bytes32",
                "name": "s",
                "type": "bytes32"
            }
        ],
        "name": "register",
        "outputs": [],
        "stateMutability": "nonpayable",
        "type": "function"
    },
    {
        "inputs": [
            {
                "internalType": "address",
                "name": "",
                "type": "address"
            },
            {
                "internalType": "uint256",
                "name": "",
                "type": "uint256"
            }
        ],
        "name": "registeredNFT",
        "outputs": [
            {
                "internalType": "bool",
                "name": "",
                "type": "bool"
            }
        ],
        "stateMutability": "view",
        "type": "function"
    },
    {
        "inputs": [
            {
                "internalType": "address",
                "name": "device",
                "type": "address"
            },
            {
                "internalType": "uint8",
                "name": "v",
                "type": "uint8"
            },
            {
                "internalType": "bytes32",
                "name": "r",
                "type": "bytes32"
            },
            {
                "internalType": "bytes32",
                "name": "s",
                "type": "bytes32"
            }
        ],
        "name": "remove",
        "outputs": [],
        "stateMutability": "nonpayable",
        "type": "function"
    },
    {
        "inputs": [
            {
                "internalType": "address",
                "name": "_ioIDStore",
                "type": "address"
            }
        ],
        "name": "setIoIDStore",
        "outputs": [],
        "stateMutability": "nonpayable",
        "type": "function"
    },
    {
        "inputs": [
            {
                "internalType": "address",
                "name": "device",
                "type": "address"
            },
            {
                "internalType": "bytes32",
                "name": "hash",
                "type": "bytes32"
            },
            {
                "internalType": "string",
                "name": "uri",
                "type": "string"
            },
            {
                "internalType": "uint8",
                "name": "v",
                "type": "uint8"
            },
            {
                "internalType": "bytes32",
                "name": "r",
                "type": "bytes32"
            },
            {
                "internalType": "bytes32",
                "name": "s",
                "type": "bytes32"
            }
        ],
        "name": "update",
        "outputs": [],
        "stateMutability": "nonpayable",
        "type": "function"
    }
]